streamlit_persistence/__init__.py
streamlit_persistence/base.py
streamlit_persistence-0.0.3.dist-info/LICENSE.txt
streamlit_persistence-0.0.3.dist-info/METADATA
streamlit_persistence-0.0.3.dist-info/WHEEL
streamlit_persistence-0.0.3.dist-info/top_level.txt
streamlit_persistence-0.0.3.dist-info/RECORD
