Metadata-Version: 2.1
Name: streamlit-persistence
Version: 0.0.3
Summary: Allows for persistence of class/instance attributes when using Streamlit in Python
Home-page: https://github.com/yaphott/streamlit-persistence
Author: yaphott
Author-email: yaphott@gmail.com
License: UNKNOWN
Keywords: streamlit,persistence,attributes,data-science,developer-tools
Platform: UNKNOWN
Classifier: Development Status :: 2 - Pre-Alpha
Classifier: Programming Language :: Python :: 3
Classifier: Programming Language :: Python :: 3.10
Classifier: Programming Language :: Python :: 3.11
Classifier: License :: OSI Approved :: MIT License
Classifier: Operating System :: POSIX :: Linux
Classifier: Operating System :: MacOS :: MacOS X
Classifier: Operating System :: Microsoft :: Windows
Requires-Python: >=3.9
License-File: LICENSE.txt
Requires-Dist: streamlit (>=1.8.1)
